pyglimer/__init__.py
pyglimer/constants.py
pyglimer/tmp.py
pyglimer/ccp/__init__.py
pyglimer/ccp/ccp.py
pyglimer/ccp/io.py
pyglimer/ccp/compute/__init__.py
pyglimer/ccp/compute/bin.py
pyglimer/ccp/plot_utils/__init__.py
pyglimer/ccp/plot_utils/line_buffer.py
pyglimer/ccp/plot_utils/midpointcolornorm.py
pyglimer/ccp/plot_utils/plot_bins.py
pyglimer/ccp/plot_utils/plot_cross_section.py
pyglimer/ccp/plot_utils/plot_line_buffer.py
pyglimer/ccp/plot_utils/plot_map.py
pyglimer/ccp/plot_utils/plot_rays.py
pyglimer/data/__init__.py
pyglimer/data/finddir.py
pyglimer/data/examples/PRF.sac
pyglimer/data/examples/PRF_depth.sac
pyglimer/data/plot_data/PaperDoubleFig.mplstyle
pyglimer/data/velocity_models/avvmodel.npz
pyglimer/data/velocity_models/iasp91.dat
pyglimer/data/velocity_models/raysum.dat
pyglimer/data/velocity_models/GyPSuM/Grid.txt
pyglimer/data/velocity_models/GyPSuM/P.01.0-100km.txt
pyglimer/data/velocity_models/GyPSuM/P.02.100-175km.txt
pyglimer/data/velocity_models/GyPSuM/P.03.175-250km.txt
pyglimer/data/velocity_models/GyPSuM/P.04.250-325km.txt
pyglimer/data/velocity_models/GyPSuM/P.05.325-400km.txt
pyglimer/data/velocity_models/GyPSuM/P.06.400-525km.txt
pyglimer/data/velocity_models/GyPSuM/P.07.525-650km.txt
pyglimer/data/velocity_models/GyPSuM/P.08.650-750km.txt
pyglimer/data/velocity_models/GyPSuM/P.09.750-850km.txt
pyglimer/data/velocity_models/GyPSuM/README.txt
pyglimer/data/velocity_models/GyPSuM/S.01.0-100km.txt
pyglimer/data/velocity_models/GyPSuM/S.02.100-175km.txt
pyglimer/data/velocity_models/GyPSuM/S.03.175-250km.txt
pyglimer/data/velocity_models/GyPSuM/S.04.250-325km.txt
pyglimer/data/velocity_models/GyPSuM/S.05.325-400km.txt
pyglimer/data/velocity_models/GyPSuM/S.06.400-525km.txt
pyglimer/data/velocity_models/GyPSuM/S.07.525-650km.txt
pyglimer/data/velocity_models/GyPSuM/S.08.650-750km.txt
pyglimer/data/velocity_models/GyPSuM/S.09.750-850km.txt
pyglimer/data/velocity_models/GyPSuM/StartingVpModel.txt
pyglimer-0.4.6.dist-info/licenses/LICENSE
pyglimer-0.4.6.dist-info/METADATA
pyglimer-0.4.6.dist-info/WHEEL
pyglimer-0.4.6.dist-info/top_level.txt
pyglimer-0.4.6.dist-info/RECORD
