Metadata-Version: 2.4
Name: pyglimer
Version: 0.4.6
Summary: Pythonic Lithospheric Imaging using Earthquake Records
Home-page: https://github.com/PyGLImER/PyGLImER
Author: Peter Makus, Lucas Sawade
Author-email: makus@gfz-potsdam.de
Project-URL: Documentation, https://pyglimer.github.io/PyGLImER/
Keywords: Seismology,Receiver Function,Earth Sciences,Lithosphere,Imaging,converted wave imaging
Classifier: Programming Language :: Python :: 3
Classifier: License :: OSI Approved :: European Union Public Licence 1.2 (EUPL 1.2)
Classifier: Operating System :: OS Independent
Classifier: Development Status :: 4 - Beta
Classifier: Topic :: Utilities
Requires-Python: >=3.10
License-File: LICENSE
Requires-Dist: global-land-mask
Requires-Dist: OWSLib
Requires-Dist: cartopy
Requires-Dist: colorama
Requires-Dist: dill
Requires-Dist: geographiclib
Requires-Dist: joblib
Requires-Dist: matplotlib
Requires-Dist: numpy
Requires-Dist: obspy>=1.3.1
Requires-Dist: pandas
Requires-Dist: pip
Requires-Dist: plotly
Requires-Dist: prov
Requires-Dist: psutil
Requires-Dist: pyvista
Requires-Dist: pyyaml
Requires-Dist: h5py
Requires-Dist: scipy
Requires-Dist: tqdm
Provides-Extra: docs
Requires-Dist: sphinx<6.0; extra == "docs"
Requires-Dist: pydata-sphinx-theme; extra == "docs"
Requires-Dist: sphinx-copybutton; extra == "docs"
Requires-Dist: sphinx-gallery; extra == "docs"
Requires-Dist: jinja2<3.1; extra == "docs"
Provides-Extra: tests
Requires-Dist: pytest; extra == "tests"
Requires-Dist: py; extra == "tests"
Requires-Dist: flake8; extra == "tests"
Dynamic: license-file
